{
  "db": {
    "name": "db",
    "connector": "memory"
  },
  "clients": {
    "name": "clients",
    "connector": "rest",
    "operations": [
      {
        "template": {
          "method": "GET",
          "url": "http://www.mocky.io/v2/5808862710000087232b75ac"
        },
        "functions": {
          "find": []
        }
      }
    ]
  },
  "polities": {
    "name": "polities",
    "connector": "rest",
    "operations": [
      {
        "template": {
          "method": "GET",
          "url": "http://www.mocky.io/v2/580891a4100000e8242b75c5"
        },
        "functions": {
          "find": []
        }
      }
    ]
  }
}
